imageaugmentationpipeline/__init__.py
imageaugmentationpipeline/core.py
imageaugmentationpipeline/utils.py
imageaugmentationpipeline-0.2.4.dist-info/licenses/LICENSE
test/__init__.py
test/integration_tests.py
test/unit_tests.py
imageaugmentationpipeline-0.2.4.dist-info/METADATA
imageaugmentationpipeline-0.2.4.dist-info/WHEEL
imageaugmentationpipeline-0.2.4.dist-info/top_level.txt
imageaugmentationpipeline-0.2.4.dist-info/RECORD
