Metadata-Version: 2.4
Name: imageaugmentationpipeline
Version: 0.2.4
Summary: A lightweight image augmentation package
Author-email: Dylan Tran <trandf@uci.edu>
License: Copyright (c) 2018 The Python Packaging Authority
Project-URL: Homepage, https://github.com/dtro18/imageAugmentation
License-File: LICENSE
Requires-Dist: pillow
Dynamic: license-file
